{
  "book_id": "al_wabil_al_sayyib",
  "chapter_id": 12,
  "title_ar": "الثالثة والسبعون",
  "title_en": "",
  "entries": [
    {
      "id": 771,
      "text_ar": ": الذكر نوعان: أحدهما ذكر أسماء الرب تبارك وتعالى وصفاته والثناء عليه بهما وتنزيهه وتقديسه عما لا يليق به تبارك وتعالى.",
      "text_en": "",
      "reference": "الفصل الأول"
    },
    {
      "id": 772,
      "text_ar": "وهذا أيضا نوعان:",
      "text_en": "",
      "reference": "الفصل الأول"
    },
    {
      "id": 773,
      "text_ar": "(أحدهما) إنشاء الثناء عليه بها من الذاكر، وهذا النوع هو المذكور في الأحاديث، نحو سبحان الله والحمد لله ولا إله إلا الله والله أكبر، وسبحان الله وبحمده، ولا إله إلا الله وحده لا شريك له له الملك وله الحمد وهو على كل شيء قدير، ونحو ذلك.",
      "text_en": "",
      "reference": "الفصل الأول"
    },
    {
      "id": 774,
      "text_ar": "فأفضل هذا النوع أجمعه للثناء وأعمه نحو سبحان الله عدد خلقه، فهذا أفضل من مجرد سبحان الله، وقولك الحمد لله عدد ما خلق في السماء وعدد ما خلق في الأرض وعدد ما بينهما وعدد ما هو خالق، أفضل من مجرد قولك الحمد لله.",
      "text_en": "",
      "reference": "الفصل الأول"
    },
    {
      "id": 775,
      "text_ar": "وهذا في حديث جويرية أن النبي صلى الله عليه وسلم قال لها: «لقد قلت بعدك أربع كلمات ثلاث مرات لو وزنت بما قلت منذ اليوم لوزنتهن: سبحان الله عدد خلقه، سبحان الله رضا نفسه، سبحان الله زنة عرشه، سبحان الله مداد كلماته» رواه مسلم.",
      "text_en": "",
      "reference": "الفصل الأول"
    },
    {
      "id": 776,
      "text_ar": "وفي الترمذي وينن أبي داود عن سعد بن أبي وقاص أنه دخل مع رسول الله على امرأة بين يديها نوى أو حصى تسبح بها فقال: «سبحان الله عدد ما خلق في السماء، وسبحان الله عدد ما خلق في الأرض، وسبحان الله عدد ما بين ذلك، وسبحان الله عدد ما هو خالق، والله أكبر",
      "text_en": "",
      "reference": "الفصل الأول"
    },
    {
      "id": 777,
      "text_ar": "مثل ذلك، ولا إله إلا الله، ولا حول ولا قوة إلا بالله مثل ذلك»",
      "text_en": "",
      "reference": "الفصل الأول"
    },
    {
      "id": 778,
      "text_ar": "(الثاني) الخبر عن الرب تعالى بأحكام أسمائه وصفاته، نحو قولك: الله عز وجل يسمع أصوات عباده ويرى حركاتهم، ولا تخفى عليه خافية من أعمالهم، وهو أرحم بهم من آبائهم وأمهاتهم، وهو على كل شيء قدير، وهو أفرح بتوبة عبده من الفاقد راحلته ونحو ذلك.",
      "text_en": "",
      "reference": "الفصل الأول"
    },
    {
      "id": 779,
      "text_ar": "وأفضل هذا النوع الثناء عليه بما أثنى به على نفسه وبما أثنى به رسول الله صلى الله عليه وسلم من غير تحريف ولا تعطيل، ومن غير تشبيه ولا تمثيل وهذا النوع أيضا ثلاثة أنواع: حمد، وثناء، ومجد، فالحمد لله الإخبار عنه بصفات كماله سبحانه وتعالى مع محبته والرضاء به، فلا يكون المحب الساكت حامدا ولا المثني بلا محبة حامدا حتى تجتمع له المحبة والثناء، فإن كرر المحامد شيئا بعد الشيء كانت ثناء، فإن كان المدح بصفات الجلال والعظمة والكبرياء والملك كان مجدا، وقد جمع الله تعالى لعبده الأنواع الثلاثة في أول الفاتحة، فإذا قال العبد: {الحمد لله رب العالمين} قال الله تعالى: حمدني عبدي، وإذا قال: {الرحمن الرحيم} قال: أثنى علي عبدي، وإذا قال: {مالك يوم الدين} قال: مجدني عبدي.",
      "text_en": "",
      "reference": "الفصل الأول"
    },
    {
      "id": 780,
      "text_ar": "(النوع الثاني) من الذكر ذكر أمره ونهيه وأحكامه، وهو أيضا نوعان:",
      "text_en": "",
      "reference": "الفصل الأول"
    },
    {
      "id": 781,
      "text_ar": "(أحدهما) ذكره بذلك إخبارا عنه أمر بكذا ونهى عنه كذا وأحب كذا وسخط كذا ورضي كذا.",
      "text_en": "",
      "reference": "الفصل الأول"
    },
    {
      "id": 782,
      "text_ar": "(والثاني) ذكره عند أمره فيبادر إليه، وعند نهيه فيهرب منه، فذكر أمره ونهيه شيء، وذكره عند أمره ونهيه شيء آخر، فإذا اجتمعت هذه الأنواع للذاكر فذكره أفضل الذكر وأجله وأعظمه.",
      "text_en": "",
      "reference": "الفصل الأول"
    },
    {
      "id": 783,
      "text_ar": "(فائدة) فهذا الذكر من الفقه الأكبر وما دونه أفضل الذكر إذا صحت فيه النية.",
      "text_en": "",
      "reference": "الفصل الأول"
    },
    {
      "id": 784,
      "text_ar": "ومن ذكره سبحانه وتعالى ذكر آلائه وإنعامه وإحسانه وأياديه ومواقع فضله على عبيده، وهذا أيضا من أجل أنواع الذكر.",
      "text_en": "",
      "reference": "الفصل الأول"
    },
    {
      "id": 785,
      "text_ar": "فهذه خمسة أنواع وهي تكون بالقلب واللسان تارة، وذلك أفضل الذكر.",
      "text_en": "",
      "reference": "الفصل الأول"
    },
    {
      "id": 786,
      "text_ar": "وبالقلب وحده تارة، وهي الدرجة الثانية، وباللسان وحده تارة، وهي الدرجة الثالثة.",
      "text_en": "",
      "reference": "الفصل الأول"
    },
    {
      "id": 787,
      "text_ar": "فأفضل الذكر ما تواطأ عليه القلب واللسان،",
      "text_en": "",
      "reference": "الفصل الأول"
    },
    {
      "id": 788,
      "text_ar": "وإنما كان ذكر القلب وحده أفضل من ذكر اللسان وحده لأن ذكر القلب يثمر المعرفة ويهيج المحبة ويثير الحياء ويبعث على المخافة ويدعو إلى المراقبة ويزع عن التقصير في الطاعات والتهاون في المعاصي والسيئات، وذكر اللسان وحده لا يوجب شيئا منها فثمرته ضعيفة.",
      "text_en": "",
      "reference": "الفصل الأول"
    },
    {
      "id": 789,
      "text_ar": "(الفصل الثاني) الذكر أفضل من الدعاء.",
      "text_en": "",
      "reference": "الفصل الثاني الذكر أفضل من الدعاء"
    },
    {
      "id": 790,
      "text_ar": "الذكر ثناء على الله عز وجل بجميل أوصافه وآلائه وأسمائه، والدعاء سؤال العبد حاجته.",
      "text_en": "",
      "reference": "الفصل الثاني الذكر أفضل من الدعاء"
    },
    {
      "id": 791,
      "text_ar": "فأين هذا من هذا؟",
      "text_en": "",
      "reference": "الفصل الثاني الذكر أفضل من الدعاء"
    },
    {
      "id": 792,
      "text_ar": "ولهذا جاء في الحديث «من شغله ذكري عن مسألتي أعطيته أفضل ما أعطي السائلين» ولهذا كان المستحب في الدعاء أن يبدأ الداعي بحمد الله والثناء عليه بين يدي حاجته، ثم يسأل حاجته.",
      "text_en": "",
      "reference": "الفصل الثاني الذكر أفضل من الدعاء"
    },
    {
      "id": 793,
      "text_ar": "كما في حديث فضالة بن عبيد «أن رسول الله صلى الله عليه وسلم سمع رجلا يدعو في صلاته لم يحمد الله تعالى ولم يصل على النبي صلى الله عليه وسلم فقال رسول الله صلى الله عليه وسلم عجل هذا ثم دعاه فقال له أو لغيره: إذا صلى أحدكم فليبدأ بتمجيد ربه عز وجل والثناء عليه، ثم يصلي على النبي صلى الله عليه وسلم، ثم يدعو بعد بما بشاء» رواه الإمام أحمد والترمذي وقال: حديث حسن صحيح.",
      "text_en": "",
      "reference": "الفصل الثاني الذكر أفضل من الدعاء"
    },
    {
      "id": 794,
      "text_ar": "ورواه الحاكم في صحيحه.",
      "text_en": "",
      "reference": "الفصل الثاني الذكر أفضل من الدعاء"
    },
    {
      "id": 795,
      "text_ar": "وهكذا دعاء ذي النون عليه السلام قال فيه النبي صلى الله عليه وسلم «دعوة أخي ذي النون ما دعا بها مكروب إلا فرج الله كربته: {لا إله إلا أنت سبحانك إني كنت من الظالمين} » وفي الترمذي «دعوة أخي ذي النون إذ دعا وهو في بطن الحوت {لا إله إلا أنت سبحانك، إني كنت من الظالمين} فإنه لم يدع بها مسلم قط إلا استجاب له» .",
      "text_en": "",
      "reference": "الفصل الثاني الذكر أفضل من الدعاء"
    },
    {
      "id": 796,
      "text_ar": "وهكذا عامة الأدعية النبوية على قائلها أفضل الصلاة والسلام، ومنه قوله صلى الله عليه وسلم في دعاء الكرب «لا إله إلا الله الحليم العظيم، لا إله إلا الله رب العرش العظيم، لا إله إلا الله رب السموات ورب الأرض ورب العرش الكريم» ومنه حديث بريدة الأسلمي الذي رواه أهل السنن وابن حبان في صحيحه أن رسول الله صلى الله عليه وسلم سمع رجلا يدعو وهو يقول: «اللهم إني أسألك بأني أشهد أنك أنت الله لا إله إلا أنت الأحد الصمد الذي لم يلد ولم يولد ولم يكن له كفوا أحد فقال: والذي نفسي بيده لقد سأل الله باسمه الأعظم الذي إذا",
      "text_en": "",
      "reference": "الفصل الثاني الذكر أفضل من الدعاء"
    },
    {
      "id": 797,
      "text_ar": "دعي به أجاب، وإذا سئل به أعطى» وروى أبو داود والنسائي من حديث أنس «أنه كان مع النبي صلى الله عليه وسلم جالسا ورجل يصلي ثم دعا: اللهم إني أسألك بأن لك الحمد، ولا إله إلا أنت المنان بديع السموات والأرض، يا ذا الجلال والإكرام، يا حي يا قيوم.",
      "text_en": "",
      "reference": "الفصل الثاني الذكر أفضل من الدعاء"
    },
    {
      "id": 798,
      "text_ar": "فقال النبي صلى الله عليه وسلم: لقد دعا الله باسمه الأعظم الذي إذا دعي به أجاب، وإذا سئل به أعطى» فأخبر النبي صلى الله عليه وسلم أن الدعاء يستجاب إذا تقدمه هذا الثناء والذكر، وأنه اسم الله الأعظم فكان ذكر الله عز وجل والثناء عليه أنجح ما طلب به العبد حوائجه.",
      "text_en": "",
      "reference": "الفصل الثاني الذكر أفضل من الدعاء"
    },
    {
      "id": 799,
      "text_ar": "وهذه فائدة أخرى من فوائد الذكر والثناء، أنه يجعل الدعاء مستجابا.",
      "text_en": "",
      "reference": "الفصل الثاني الذكر أفضل من الدعاء"
    },
    {
      "id": 800,
      "text_ar": "فالدعاء الذي تقدمه الذكر والثناء أفضل وأقرب إلى الإجابة من الدعاء المجرد، فإن انضاف إلى ذلك إخبار العبد بحاله ومسكنته وافتقاره واعترافه كان أبلغ في الإجابة وأفضل، فإنه يكون قد توسل المدعو بصفات كماله وإحسانه وفضله، وعرض بل صرح بشدة حاجته وضرورته وفقره ومسكنته، فهذا المقتضى منه، وأوصاف المسئول مقتضى من الله، فاجتمع المقتضي من السائل والمقتضى من المسؤول في الدعاء، وكان أبلغ وألطف موقعا وأتم معرفة وعبودية.",
      "text_en": "",
      "reference": "الفصل الثاني الذكر أفضل من الدعاء"
    },
    {
      "id": 801,
      "text_ar": "وأنت ترى في المشاهد ولله المثل الأعلى أن الرجل إذا توسل إلى ما يريد معروفة بكرمه وجوده وبره وذكر حاجته هو وفقره ومسكنته كان أعطف لقلب المسؤول وأقرب لقضاء حاجته.",
      "text_en": "",
      "reference": "الفصل الثاني الذكر أفضل من الدعاء"
    },
    {
      "id": 802,
      "text_ar": "فإذا قال له: أنت جودك قد سارت به الركبان، وفضلك كالشمس لا تنكر ونحو ذلك، وقد بلغت بي الحاجة والضرورة مبلغا لا صبر معه ونحو ذلك، كان أبلغ في قضاء حاجته من أن يقول ابتداء أعطني كذا وكذا.",
      "text_en": "",
      "reference": "الفصل الثاني الذكر أفضل من الدعاء"
    },
    {
      "id": 803,
      "text_ar": "فإذا عرفت هذا فتأمل قول موسى صلى الله عليه وسلم في دعائه {رب إني لما أنزلت إلي من خير فقير} وقول ذي النون في دعائه {لا إله إلا أنت سبحانك، إني كنت من الظالمين} وقول أبينا آدم {ربنا ظلمنا أنفسنا، وإن لم تغفر لنا وترحمنا لنكونن من الخاسرين} وفي الصحيحين أن أبا بكر الصديق قال: يا رسول الله علمني دعاء أدعو به في صلاتي، فقال: «قل اللهم إني ظلمت نفسي ظلما كثيرا، وإنه لا يغفر",
      "text_en": "",
      "reference": "الفصل الثاني الذكر أفضل من الدعاء"
    },
    {
      "id": 804,
      "text_ar": "الذنوب إلا أنت، فاغفر لي مغفرة من عندك وارحمني، إنك أنت الغفور الرحيم» فجمع في هذا الدعاء الشريف العظيم القدر بين الاعتراف بحاله والتوسل إلى ربه عز وجل بفضله وجوده وأنه المنفرد بغفران الذنوب، ثم سأل حاجته بعد التوسل بالأمرين معا.",
      "text_en": "",
      "reference": "الفصل الثاني الذكر أفضل من الدعاء"
    },
    {
      "id": 805,
      "text_ar": "فهكذا أدب الدعاء وآداب العبودية.",
      "text_en": "",
      "reference": "الفصل الثاني الذكر أفضل من الدعاء"
    },
    {
      "id": 806,
      "text_ar": "هذا من حيث النظر لكل منهما مجردا، وقد يعرض للمفضول ما يجعله أولى من الفاضل، بل يعينه فلا يجوز أن يعدل عنه إلى الفاضل، وهذا كالتسبيح في الركوع والسجود فإنه أفضل من قراءة القرآن فيهما، بل القراءة فيهما منهي عنها نهي تحريم أو كراهة، وكذلك التسميع والتحميد في محلهما أفضل من القراءة، وكذلك التشهد، وكذلك «رب اغفر لي وارحمني واهدني وعافني وارزقني» بين السجدتين أفضل من القراءة، وكذلك الذكر عقيب السلام من الصلاة ذكر التهليل والتسبيح والتكبير والتحميد أفضل من الاشتغال عنه بالقراءة، وكذلك إجابة المؤذن والقول كما يقول أفضل من القراءة.",
      "text_en": "",
      "reference": "الفصل الثالث في قراءة القرآن أفضل من الذكر، والذكر أفضل من الدعاء."
    },
    {
      "id": 807,
      "text_ar": "وإن كان فضل القرآن على كل كلام كفضل الله تعالى على خلقه، لكن لكل مقام مقال، متى فات مقاله فيه وعدل عنه إلى غيره اختلت الحكمة وفقدت المصلحة المطلوبة منه.",
      "text_en": "",
      "reference": "الفصل الثالث في قراءة القرآن أفضل من الذكر، والذكر أفضل من الدعاء."
    },
    {
      "id": 808,
      "text_ar": "وهكذا الأذكار المفيدة بمحال مخصوصة أفضل من القراءة المطلقة، والقراءة المطلقة أفضل من الأذكار المطلقة، اللهم إلا أن يعرض للعبد ما يجعل الذكر أو الدعاء أنفع له من قراءة القرآن.",
      "text_en": "",
      "reference": "الفصل الثالث في قراءة القرآن أفضل من الذكر، والذكر أفضل من الدعاء."
    },
    {
      "id": 809,
      "text_ar": "مثاله أن يتفكر في ذنوبه فيحدث ذلك له توبة من استغفار أو يعرض له ما يخاف أذاه من شياطين الإنس والجن فيعدل إلى الأذكار والدعوات التي تحصنه وتحفظه.",
      "text_en": "",
      "reference": "الفصل الثالث في قراءة القرآن أفضل من الذكر، والذكر أفضل من الدعاء."
    },
    {
      "id": 810,
      "text_ar": "وكذلك أيضا قد يعرض للعبد حاجة ضرورية إذا اشتغل عن سؤالها أو ذكر لم يحضر قلبه فيهما، وإذا أقبل على سؤالها والدعاء إليها اجتمع قلبه كله على الله تعالى وأحدث له",
      "text_en": "",
      "reference": "الفصل الثالث في قراءة القرآن أفضل من الذكر، والذكر أفضل من الدعاء."
    },
    {
      "id": 811,
      "text_ar": "تضرعا وخشوعا وابتهالا، فهذا يكون اشتغاله بالدعاء والحالة هذه أنفع، وإن كان كل من القراءة والذكر أفضل وأعظم أجرا.",
      "text_en": "",
      "reference": "الفصل الثالث في قراءة القرآن أفضل من الذكر، والذكر أفضل من الدعاء."
    },
    {
      "id": 812,
      "text_ar": "وهذا باب نافع يحتاج إلى فقه نفس، وفرقان بين فضيلة الشيء في نفسه وبين فضيلته العارضة، فيعطي كل ذي حق حقه، ويوضع كل شيء موضعه: فللعين موضع وللرجل موضع، وللماء موضع وللحم موضع.",
      "text_en": "",
      "reference": "الفصل الثالث في قراءة القرآن أفضل من الذكر، والذكر أفضل من الدعاء."
    },
    {
      "id": 813,
      "text_ar": "وحفظ المراتب هو من تمام الحكمة التي هي نظام الأمر والنهي.",
      "text_en": "",
      "reference": "الفصل الثالث في قراءة القرآن أفضل من الذكر، والذكر أفضل من الدعاء."
    },
    {
      "id": 814,
      "text_ar": "والله تعالى الموفق.",
      "text_en": "",
      "reference": "الفصل الثالث في قراءة القرآن أفضل من الذكر، والذكر أفضل من الدعاء."
    },
    {
      "id": 815,
      "text_ar": "وهكذا الصابون والأشنان أنفع للثوب في وقت والتجمير وماء الورد وكيه أنفع له في وقت.",
      "text_en": "",
      "reference": "الفصل الثالث في قراءة القرآن أفضل من الذكر، والذكر أفضل من الدعاء."
    },
    {
      "id": 816,
      "text_ar": "وقلت لشيخ الإسلام ابن تيمية رحمه الله تعالى يوما: سئل بعض أهل العلم أيهما أنفع للعبد التسبيح أو الاستغفار؟ فقال: إذا كان الثوب نقيا فالبخور وماء الورد أنفع له، وإذا كان دنسا فالصابون والماء الحار أنفع له.",
      "text_en": "",
      "reference": "الفصل الثالث في قراءة القرآن أفضل من الذكر، والذكر أفضل من الدعاء."
    },
    {
      "id": 817,
      "text_ar": "فقال لي رحمه الله تعالى: فكيف والثياب لا تزال دنسة؟ ومن هذا الباب أن سورة {قل هو الله أحد} تعدل ثلث القرآن ومع هذا فلا تقوم مقام آيات المواريث والطلاق والخلع والعدد ونحوها، بل هذه الآيات في وقتها وعند الحاجة إليها أنفع من تلاوة سورة الإخلاص.",
      "text_en": "",
      "reference": "الفصل الثالث في قراءة القرآن أفضل من الذكر، والذكر أفضل من الدعاء."
    },
    {
      "id": 818,
      "text_ar": "ولما كانت الصلاة مشتملة على القراءة والذكر والدعاء، وهي جامعة لأجزاء العبودية على أتم الوجوه، كانت أفضل من كل من القراءة والذكر والدعاء بمفرده، لجمعها ذلك كله مع عبودية سائر الأعضاء.",
      "text_en": "",
      "reference": "الفصل الثالث في قراءة القرآن أفضل من الذكر، والذكر أفضل من الدعاء."
    },
    {
      "id": 819,
      "text_ar": "فهذا أصل نافع جدا يفتح للعبد باب معرفة مراتب الأعمال وتنزيلها منازلها، لئلا يشتغل بمفضولها عن فاضلها فيربح إبليس الفضل الذي بينهما، أو ينظر إلى فاضلها فيشتغل به عن مفضولها إن كان ذلك وقته، فتفوته مصلحته بالكلية، لظنه أن اشتغاله بالفاضل أكثر ثوابا وأعظم أجرا.",
      "text_en": "",
      "reference": "الفصل الثالث في قراءة القرآن أفضل من الذكر، والذكر أفضل من الدعاء."
    },
    {
      "id": 820,
      "text_ar": "وهذا يحتاج إلى معرفة بمراتب الأعمال وتفاوتها ومقاصدها، وفقه في إعطاء كل عمل منها حقه، وتنزله في مرتبته، وتفويته لما هو أهم منه، أو تفويت ما هو أولى منه وأفضل لإمكان تداركه والعود إليه، وهذا المفضول إن فات لا يمكن تداركه فالاشتغال به أولى وهذا كترك القراءة لرد السلام وتشميت العاطس وإن كان القرآن أفضل، لأنه يمكنه الاشتغال بهذا المفضول والعود إلى الفاضل، بخلاف ما إذا اشتغل بالقراءة فاتته مصلحة رد السلام وتشميت العاطس، وهكذا سائر الأعمال إذا تزاحمت.",
      "text_en": "",
      "reference": "الفصل الثالث في قراءة القرآن أفضل من الذكر، والذكر أفضل من الدعاء."
    },
    {
      "id": 821,
      "text_ar": "والله تعالى الموفق.",
      "text_en": "",
      "reference": "الفصل الثالث في قراءة القرآن أفضل من الذكر، والذكر أفضل من الدعاء."
    }
  ]
}