{
  "book_id": "al_wabil_al_sayyib",
  "chapter_id": 15,
  "title_ar": "الفصل الثاني عشر في أدعية الصلاة بعد التشهد",
  "title_en": "",
  "entries": [
    {
      "id": 1,
      "text_ar": "وفي صحيح مسلم عن ثوبان رضي الله عنه قال: كان رسول الله صلى الله عليه وسلم إذا انصرف من صلاته استغفر الله ثلاثا وقال «اللهم أنت السلام ومنك السلام تباركت يا ذا الجلال والإكرام» وفي الصحيحين عن المغيرة بن شعبة أن رسول الله صلى الله عليه وسلم كان إذا فرغ من الصلاة قال: «لا إله إلا الله وحده لا شريك له، له الملك وله الحمد وهو عل كل شيء قدير.\n\nاللهم لا مانع لما أعطيت ولا معطي لما منعت، ولا ينفع ذا الجد منك الجد» وفي صحيح مسلم عن عبد الله بن الزبير رضي الله تعالى عنهما أن رسول اله صلى الله عليه وسلم كان يهلل دبر كل صلاة حين يسلم بهؤلاء الكلمات «لا إله إلا الله وحده لا شريك له، له الملك وله الحمد وهو على كل شيء قدير، لا حول ولا قوة إلا بالله، لا إله إلا الله، ولا نعبد إلا إياه، له النعمة وله الفضل وله الثناء الحسن، لا إله إلا الله مخلصين له الدين ولو كره الكافرون» .\n\nوفي صحيح مسلم عن أبي هريرة عن رسول الله صلى الله عليه وسلم قال «من سبح لله في دبر كل صلاة ثلاثا وثلاثين، وكبر الله ثلاثا وثلاثين، وحمد الله ثلاثا وثلاثين، وقال تمام المائة: لا إله إلا الله وحده لا شريك له، له الملك وله الحمد وهو على كل شيء قدير، غفرت خطاياه وإن كانت\n\nمثل زبد البحر» .\n\nوفي السنن عن عبد الله بن عمر عن النبي صلى الله عليه وسلم قال «خصلتان -أو خلتان- لا يحافظ عليهما عبد مسلم إلا دخل الجنة، هما يسير، ومن يعمل بهما قليل: يسبح الله في دبر كل صلاة عشرا، ويحمده عشرا، ويكبره عشرا، فذلك خمسون ومائة باللسان، وألف وخمسمائة في الميزان.\n\nويكبر أربعا وثلاثين إذا أخذ مضجعه، ويحمد ثلاثا وثلاثين، ويسبح ثلاثا وثلاثين فذلك مائة باللسان وألف في الميزان» قال: ولقد رأيت رسول الله صلى الله عليه وسلم يعقدها بيده.\n\nقالوا: يا رسول الله، كيف هما يسير ومن يعمل بهما قليل؟ قال يأتي أحدكم - يعني الشيطان - في منامه فينومه قبل أن يقولهما، ويأتيه في صلاته فيذكره حاجته قبل أن يقولهما وفي السنن عن عقبة بن عامر قال: أمرني رسول الله صلى الله عليه وسلم أن أقرأ بالمعوذتين دبر كل صلاة.\n\nوفي النسائي الكبير عن أبي هريرة قال: قال رسول الله صلى الله عليه وسلم «من قرأ آية الكرسي عقب كل صلاة لم يمنعه من دخول الجنة إلا أن يموت» .\n\nيعني: لم يكن بينه وبين دخول الجنة إلا الموت.\n\nفي الصحيحين عن عبد الله بن مسعود قال: علمني رسول الله صلى الله عليه وسلم التشهد - وكفي بين كفيه - كما يعلمني السورة من القرآن «التحيات لله والصلوات والطيبات، السلام عليك أيها النبي ورحمة الله وبركاته، السلام علينا وعلى عباد الله الصالحين.\n\nأشهد أن لا إله إلا الله وأشهد أن محمدا عبده ورسوله» وفي صحيح مسلم عن ابن عباس قال: كان رسول الله صلى الله عليه وسلم يعلمنا التشهد كما يعلمنا السورة من القرآن وكان يقول «التحيات المباركات والصلوات والطيبات لله.\n\nالسلام عليك أيها النبي ورحمة الله وبركاته، السلام علينا وعلى عباد الله الصالحين.\n\nأشهد أن لا إله إلا الله وأن محمدا رسول الله» وفي صحيح مسلم عن أبي موسى أن النبي صلى الله عليه وسلم علمهم التشهد «التحيات الطيبات والصلوات لله.\n\nالسلام عليك أيها النبي ورحمة الله وبركاته، السلام علينا وعلى عباد الله الصالحين.\n\nأشهد أن لا إله إلا الله وأشهد أن محمدا عبده ورسوله» .\n\nوروى أبو داود عن عمر بن الخطاب عن رسول الله صلى الله عليه وسلم في التشهد «التحيات لله والصلوات الطيبات، السلام عليك أيها النبي ورحمة الله وبركاته، أشهد أن لا إله إلا الله وأشهد أن محمدا عبده ورسوله» .\n\nوروى أبو داود عن سمرة بن جندب: أمرنا رسول الله صلى الله عليه وسلم «إذا كان في وسط الصلاة أو حين انقضائها فابدأوا قبل السلام فقولوا: التحيات والصلوات الملك لله، ثم سلموا على اليمين ثم على قارئكم وعلى أنفسكم» .",
      "text_en": "",
      "reference": ""
    },
    {
      "id": 2,
      "text_ar": "وذكر مالك في الموطأ أن عمر كان يعلم الناس التشهد وهو على المنبر يقول: قولوا التحيات لله الزاكيات لله الصلوات الطيبات لله.\n\nالسلام عليك أيها النبي ورحمة الله وبركاته،\n\nالسلام علينا وعلى عباد الله الصالحين.\n\nأشهد أن لا إله إلا الله وأشهد أن محمدا عبده ورسوله.\n\nفأي تشهد أتي به من هذه التشهدات أجزأه.\n\nوذهب الإمام أحمد وأبو حنيفة إلى تشهد ابن مسعود، وذهب الشافعي إلى تشهد ابن عباس، وذهب مالك إلى تشهد عمر رضي الله عنه، والكل كاف يجزئ.\n\nفي الصحيحين عن كعب بن عجرة رضي الله عنه قال: خرج علينا رسول الله صلى الله عليه وسلم فقلنا: قد عرفنا كيف نسلم عليك فكيف نصلي عليك؟ قال: «قولوا: اللهم صل على محمد وعلى آل محمد كما صليت على إبراهيم إنك حميد مجيد» .\n\nوفي الصحيحين أيضا عن أبي حميد الساعدي أنهم قالوا: يا رسول الله، كيف نصلي عليك؟ قال: «قولوا: اللهم صل على محمد وعلى أزواجه وذريته، كما صليت على إبراهيم، وبارك على محمد وعلى أزواجه وذريته، كما باركت على آل إبراهيم إنك حميد مجيد» .\n\nوفي صحيح مسلم عن أبي مسعود الأنصاري قال: أتانا رسول الله صلى الله عليه وسلم ونحن في مجلس سعد بن عبادة، فقال له بشير بن سعد: أمرنا الله أن نصلي عليك يا رسول الله، كيف نصلي عليك؟ قال فسكت رسول الله صلى الله عليه وسلم حتى تمنينا أنه لم يسأله.\n\nثم قال رسول الله صلى الله عليه وسلم «قولوا: اللهم صل على محمد وعلى آل محمد، كما صليت على إبراهيم وعلى آل إبراهيم.\n\nوبارك على محمد وعلى آل محمد، كما باركت على إبراهيم وعلى آل إبراهيم في العالمين إنك حميد مجيد.\n\nوالسلام كما قد علمتم» .\n\nوذكر ابن ماجه في سننه عن عبد الله بن مسعود قال: إذا صليتم على رسول الله صلى الله عليه وسلم فأحسنوا الصلاة، فإنكم لا تدرون لعل ذلك يعرض عليه.\n\nقال فقالوا له: فعلمنا.\n\nقال قولوا: اللهم اجعل صلواتك ورحمتك وبركاتك على سيد المرسلين، وإمام المتقين، وخاتم النبيين، محمد عبدك ورسولك إمام الخير، ورسول الرحمة.\n\nاللهم ابعثه مقاما يغبطه به الأولون.\n\nاللهم صل على محمد وعلى آل محمد، كما صليت على إبراهيم وعلى آل إبراهيم إنك حميد مجيد.\n\nاللهم بارك على محمد وعلى آل محمد كما باركت على إبراهيم وآل إبراهيم إنك حميد مجيد.\n\nالفصل السادس عشر في الاستخارة\n\nفي صحيح البخاري عن جابر قال: كان رسول اله صلى الله عليه وسلم يعلمنا الاستخارة في الأمر كما يعلمنا السورة من القرآن، إذا هم أحكم بالأمر فليركع ركعتين من غير الفريضة ثم ليقل: «اللهم إني أستخيرك بعلمك، وأستقدرك بقدرتك، وأسألك من فضلك العظيم، فإنك تقدر ولا أقدر وتعلم ولا أعلم وأنت علام الغيوب.\n\nاللهم إن كنت تعلم أن هذا الأمر - ويسمي حاجته- خير لي في ديني ومعاشي وعاقبة أمري فاقدره لي ويسره لي ثم بارك لي فيه، وإن كنت تعلم أن هذا الأمر شر لي في ديني ومعاشي وعاقبة أمري فاصرفه عني واصرفني عنه واقدر لي الخير حيث كان ثم أرضني به» .\n\nوفي مسند الإمام أحمد من حديث سعد\n\nبن أبي وقاص عن النبي صلى الله عليه وسلم أنه قال: «من سعادة ابن آدم استخارة الله، ومن سعادة ابن آدم رضاه بما قضى الله، ومن شقوة ابن آدم تركه استخارة الله، ومن شقوة ابن آدم سخطه بما قضى الله» .\n\nوكان شيخ الإسلام ابن تيمية رضي الله عنه يقول: ما ندم من استخار الخالق، وشاور المخلوقين، وثبت في أمره.\n\nوقد قال سبحانه وتعالى: {وشاورهم في الأمر، فإذا عزمت فتوكل على الله} وقال قتادة: ما تشاور قوم يبتغون وجه الله إلا هدوا إلى أرشد أمرهم.\n\nوفي الصحيحين عن ابن عباس أن رسول الله صلى الله عليه وسلم كان يقول عند الكرب «لا إله إلا الله العظيم الحليم، لا إله إلا الله رب العرش العظيم، لا إله إلا الله رب السموات ورب الأرض رب العرش الكريم» .",
      "text_en": "",
      "reference": ""
    },
    {
      "id": 3,
      "text_ar": "وفي الترمذي عن أنس رضي الله عنه أن النبي صلى الله عليه وسلم كان إذا حز به أمر قال «يا حي يا قيوم برحمتك أستغيث» .\n\nوفيه أيضا عن أبي هريرة أن النبي صلى الله عليه وسلم كان إذا أهمه الأمر رفع رأسه إلى السماء فقال «سبحان الله العظيم» وإذا اجتهد في الدعاء قال «يا حي يا قيوم» .\n\nوفي سنن أبي داود عن أبي بكرة أن رسول الله صلى الله عليه وسلم قال «دعوات المكروب: اللهم رحمتك أرجو، فلا تكلني إلى نفسي طرفة عين، وأصلح لي شأني كله لا إله إلا أنت» .\n\nوفي السنن أيضا عن أسماء بنت عميس قالت: قال رسول الله صلى الله عليه وسلم «ألا\n\nأعلمك كلمات تقولينهن عند الكرب -أو في الكرب- الله الله ربي لا أشرك به شيئا» .\n\nوفي رواية أنها تقال سبع مرات.\n\nوفي الترمذي عن سعد بن أبي وقاص قال: قال رسول الله صلى الله عليه وسلم «دعوة ذي النون إذ دعا وهو في بطن الحوت {لا إله إلا أنت سبحانك إني كنت من الظالمين} لم يدع بها رجل مسلم في شيء قط إلا استجيب له» وفي رواية «إني لأعلم كلمة لا يقولها مكروب إلا فرج الله عنه، كلمة أخي يونس عليه السلام» .\n\nوفي مسند الإمام أحمد وصحيح ابن حبان عن عبد الله بن مسعود عن النبي صلى الله عليه وسلم قال «ما أصاب عبدا هم ولا حزن فقال: اللهم إني عبدك ابن أمتك، ناصيتي بيدك، ماض في حكمك، عدل في قضاؤك، أسألك بكل اسم هو لك سميت به نفسك، أو أنزلته في كتابك، أو علمته أحدا من خلقك، أو استأثرت به في علم الغيب عندك، أن تجعل القرآن ربيع قلبي، ونور بصري وجلاء حزني، وذهاب همي.\n\nإلا أذهب الله همه وحزنه وأبدله مكانه فرحا» .",
      "text_en": "",
      "reference": ""
    }
  ]
}