{
  "book_id": "rawdat_al_talibin",
  "chapter_id": 177,
  "title_ar": "فصل",
  "title_en": "",
  "entries": [
    {
      "id": 12954,
      "text_ar": "</span>",
      "text_en": "",
      "reference": "فصل"
    },
    {
      "id": 12955,
      "text_ar": "إذا ملك في مرض موته من يعتق عليه، فإن ملكه بالإرث، فهل يعتق من الثلث، أم من رأس المال؟ وجهان، رجح البغوي والمتولي كونه من الثلث، والأصح: كونه من رأس المال، وبه قطع الأستاذ أبو منصور.",
      "text_en": "",
      "reference": "فصل"
    },
    {
      "id": 12956,
      "text_ar": "وفي كلام الشيخ أبي علي وغيره: ما يقتضي الجزم به ; لأنه [لم يقصد] تملكه، ولا تضرر به الورثة.",
      "text_en": "",
      "reference": "فصل"
    },
    {
      "id": 12957,
      "text_ar": "وإن ملكه بالهبة، أو الوصية، فإن قلنا في الموروث: يعتق من الثلث، فهنا أولى ; لأنه مختار، وإلا، فوجهان.",
      "text_en": "",
      "reference": "فصل"
    },
    {
      "id": 12958,
      "text_ar": "أصحهما: من رأس المال، وبه قطع",
      "text_en": "",
      "reference": "فصل"
    },
    {
      "id": 12959,
      "text_ar": "ابن الحداد وأبو منصور ; لأنه لم يبذل مالا، وزوال الملك حصل بغير رضاه.",
      "text_en": "",
      "reference": "فصل"
    },
    {
      "id": 12960,
      "text_ar": "فإن قلنا: من رأس المال، عتق وإن لم يكن له مال سواه.",
      "text_en": "",
      "reference": "فصل"
    },
    {
      "id": 12961,
      "text_ar": "وكذا لو كان عليه دين مستغرق، وكذا المفلس المحجور عليه إذا قبله ولا سبيل للغرماء عليه.",
      "text_en": "",
      "reference": "فصل"
    },
    {
      "id": 12962,
      "text_ar": "وإن قلنا: يعتق من الثلث، فلم يكن مال سواه، عتق ثلثه فقط.",
      "text_en": "",
      "reference": "فصل"
    },
    {
      "id": 12963,
      "text_ar": "وإن كان عليه دين، لم يعتق، وبيع في الدين، وكذا في المحجور عليه بالفلس.",
      "text_en": "",
      "reference": "فصل"
    },
    {
      "id": 12964,
      "text_ar": "ولو اشترى المريض من يعتق عليه، وعليه دين، ففي صحة الشراء وجهان.",
      "text_en": "",
      "reference": "فصل"
    },
    {
      "id": 12965,
      "text_ar": "ويقال: قولان.",
      "text_en": "",
      "reference": "فصل"
    },
    {
      "id": 12966,
      "text_ar": "أصحهما: الصحة، إذ لا خلل في الشراء، فيثبت الملك، ولا يعتق، لحق الغرماء.",
      "text_en": "",
      "reference": "فصل"
    },
    {
      "id": 12967,
      "text_ar": "فإن لم يكن دين، اعتبر عتقه من الثلث.",
      "text_en": "",
      "reference": "فصل"
    },
    {
      "id": 12968,
      "text_ar": "فإن خرج كله، صح الشراء، وعتق كله، وإلا، ففي صحة الشراء فيما زاد على الثلث الخلاف فيما إذا كان عليه دين.",
      "text_en": "",
      "reference": "فصل"
    },
    {
      "id": 12969,
      "text_ar": "فإن قلنا: لا يصح، ففي قدر الثلث الخلاف المذكور في تفريق الصفقة.",
      "text_en": "",
      "reference": "فصل"
    },
    {
      "id": 12970,
      "text_ar": "وإن قلنا: يصح، عتق الثلث فقط.",
      "text_en": "",
      "reference": "فصل"
    },
    {
      "id": 12971,
      "text_ar": "وفي وجه: شراء المريض أباه باطل مطلقا ; لأنه وصية، وهي موقوفة على الخروج من الثلث، والبيع لا يوقف، وهذا ضعيف.",
      "text_en": "",
      "reference": "فصل"
    },
    {
      "id": 12972,
      "text_ar": "هذا كله إذا لم يكن محاباة.",
      "text_en": "",
      "reference": "فصل"
    },
    {
      "id": 12973,
      "text_ar": "أما إذا اشتراه بخمسين، وقيمته مائة، فقدر المحاباة هبة، فيجئ فيه الوجهان في أنه من الثلث، أو رأس المال؟ فإن قلنا: من الثلث، فجميع المائة من الثلث، وإلا فالمعتبر منه خمسون.",
      "text_en": "",
      "reference": "فصل"
    },
    {
      "id": 12974,
      "text_ar": "ثم متى حكمنا بعتقه من الثلث، لا يرثه ; لأنه وصية، ولا سبيل إلى الجمع بينها وبين الإرث.",
      "text_en": "",
      "reference": "فصل"
    },
    {
      "id": 12975,
      "text_ar": "هكذا أطلقوه وعللوه، وكأنه تفريع على بطلان الوصية لوارث.",
      "text_en": "",
      "reference": "فصل"
    },
    {
      "id": 12976,
      "text_ar": "فإن قلنا: يقف على إجازة الوارث، لم يمتنع الجمع بينها وبين الإرث، فيحتمل توقف الأمر على الإجازة، ويحتمل خلافه.",
      "text_en": "",
      "reference": "فصل"
    },
    {
      "id": 12977,
      "text_ar": "وحكى الأستاذ وأبو منصور وجها: أنه يرث ; لأنه لا (يملك) رقبته حتى يقال: أوصى له بها.",
      "text_en": "",
      "reference": "فصل"
    },
    {
      "id": 12978,
      "text_ar": "والصحيح الأول.",
      "text_en": "",
      "reference": "فصل"
    },
    {
      "id": 12979,
      "text_ar": "ومتى عتق من رأس المال، ورث على الصحيح.",
      "text_en": "",
      "reference": "فصل"
    },
    {
      "id": 12980,
      "text_ar": "وقال الإصطخري: لا يرث، وجعل عتقه وصية في حقه.",
      "text_en": "",
      "reference": "فصل"
    },
    {
      "id": 12981,
      "text_ar": "وإن لم تكن وصية في حق الوارث، كما لو نكحت المريضة بدون مهر المثل، تصح المحاباة من رأس",
      "text_en": "",
      "reference": "فصل"
    },
    {
      "id": 12982,
      "text_ar": "المال إن كان الزوج أجنبيا.",
      "text_en": "",
      "reference": "فصل"
    },
    {
      "id": 12983,
      "text_ar": "فإن كان وارثا، جعل وصية، فتبطل ويجب مهر المثل.",
      "text_en": "",
      "reference": "فصل"
    },
    {
      "id": 12984,
      "text_ar": "إذا قال: أعتقوا عبدي بعد موتي، لم يفتقر إلى قبول العبد ; لأن لله تعالى حقا مؤكدا في العتق، فكان كالوصية للجهات العامة.",
      "text_en": "",
      "reference": "فصل"
    },
    {
      "id": 12985,
      "text_ar": "ولو قال: أوصيت له برقبته، فهي وصية صحيحة، ومقصودها الإعتاق، ويشترط قبوله على الأصح، لاقتضاء الصيغة ذلك، كقوله لعبده: ملكتك نفسك، أو وهبت لك نفسك، فإنه يشترط فيه القبول في المجلس.",
      "text_en": "",
      "reference": "فصل"
    },
    {
      "id": 12986,
      "text_ar": "ولو قال: وهبتك نفسك، ونوى به العتق، عتق بلا قبول.",
      "text_en": "",
      "reference": "فصل"
    },
    {
      "id": 12987,
      "text_ar": "قال: إذا مت، فأعتقوا ثلث عبدي، أو قال: ثلث عبدي حر إذا مت، لم يعتق إذا مات إلا ثلثه، ولا يسري ; لأنه ليس بمالك للباقي في حال العتق، ولا موسر بقيمته، بخلاف ما لو أعتق المريض بعض عبده، فإنه يسري إذا وفى به الثلث ; لأنه مالك للباقي. ولو ملك ثلاثة أعبد قيمتهم سواء، لا مال سواهم، فأعتق في مرضه ثلث كل واحد منهم، فقال: ثلث كل واحد منهم حر، أو أثلاثهم أحرار، فهل يعتق من كل عبد ثلثه كما ذكر؟ أم يقرع بينهم فيعتق واحد بالقرعة لتجتمع الحرية كما لو قال: أعتقت هؤلاء؟ فيه وجهان.",
      "text_en": "",
      "reference": "فصل"
    },
    {
      "id": 12988,
      "text_ar": "أصحهما: الثاني.",
      "text_en": "",
      "reference": "فصل"
    },
    {
      "id": 12989,
      "text_ar": "ولو قال: أعتقت ثلثكم، أو ثلثكم حر، أقرع قطعا.",
      "text_en": "",
      "reference": "فصل"
    },
    {
      "id": 12990,
      "text_ar": "وقيل: فيه الوجهان.",
      "text_en": "",
      "reference": "فصل"
    },
    {
      "id": 12991,
      "text_ar": "ولو قال: أثلاث هؤلاء أحرار بعد موتي، أو ثلث كل واحد، عتق من كل عبد ثلثه، ولا قرعة،",
      "text_en": "",
      "reference": "فصل"
    },
    {
      "id": 12992,
      "text_ar": "لما ذكرنا أن العتق بعد الموت لا يسري، لكن لو زاد ما أعتق على الثلث، أقرع لرد الزيادة، لا للسراية.",
      "text_en": "",
      "reference": "فصل"
    },
    {
      "id": 12993,
      "text_ar": "وفي «التهذيب» وغيره وجه: أنه يقرع، كما لو نجز في المرض، فمن خرجت له القرعة، عتق، ورق الآخران.",
      "text_en": "",
      "reference": "فصل"
    },
    {
      "id": 12994,
      "text_ar": "والصحيح الأول، وبه قال ابن الحداد، وفرع عليه فقال: لو قال للثلاثة: النصف من كل عبد منكم حر، فقد أعتق نصف ماله.",
      "text_en": "",
      "reference": "فصل"
    },
    {
      "id": 12995,
      "text_ar": "فإن لم تجز الورثة، أقرع بين العبيد بسهم رق وسهمي حرية، فمن أصابه سهم الرق، رق، ويعتق من كل واحد من الآخرين نصفه، ولا يسري.",
      "text_en": "",
      "reference": "فصل"
    },
    {
      "id": 12996,
      "text_ar": "ولو أعتق الأنصاف في مرضه، فمن عتق منه شيء، سرى إلى باقيه إلى أن يتم الثلث، فيقرع بينهم بسهمي رق، وسهم عتق.",
      "text_en": "",
      "reference": "فصل"
    },
    {
      "id": 12997,
      "text_ar": "فمن خرج له سهم العتق، عتق كله، وهو ثلث المال.",
      "text_en": "",
      "reference": "فصل"
    },
    {
      "id": 12998,
      "text_ar": "ولو لم يملك إلا عبدين قيمتهما سواء، فقال: نصف غانم حر بعد موتي، وثلث سالم حر بعد موتي، فقد أعتق خمسة أسداس، وليس له إلا أربعة أسداس، فيقرع لرد الزيادة، فإن خرج العتق لغانم، عتق نصفه، وعتق سدس سالم ليتم الثلث.",
      "text_en": "",
      "reference": "فصل"
    },
    {
      "id": 12999,
      "text_ar": "فإن خرج العتق لسالم، عتق ثلثه وثلث غانم.",
      "text_en": "",
      "reference": "فصل"
    },
    {
      "id": 13000,
      "text_ar": "وإن أعتق نصف كل واحد منهما في مرضه، أقرع، فمن خرج له سهم العتق، عتق ثلثاه، ورق باقيه مع جميع الآخر.",
      "text_en": "",
      "reference": "فصل"
    },
    {
      "id": 13001,
      "text_ar": "هذا كله، إذا أعتق الأبعاض في المرض معا، بأن قال: أثلاث هؤلاء أحرار، أو نصف كل عبد حر.",
      "text_en": "",
      "reference": "فصل"
    },
    {
      "id": 13002,
      "text_ar": "فأما إذا قدم وأخر، فيقدم الأسبق فالأسبق، حتى لو قال: نصف غانم حر، وثلث سالم حر، عتق ثلثا غانم، ولا قرعة.",
      "text_en": "",
      "reference": "فصل"
    },
    {
      "id": 13003,
      "text_ar": "</span>",
      "text_en": "",
      "reference": "فصل"
    },
    {
      "id": 13004,
      "text_ar": "أعتق جاريته بعد الموت وهي حامل، ففي الحمل وجهان.",
      "text_en": "",
      "reference": "فصل"
    },
    {
      "id": 13005,
      "text_ar": "أحدهما: لا يعتق، لما سبق أن إعتاق الميت لا يسري.",
      "text_en": "",
      "reference": "فصل"
    },
    {
      "id": 13006,
      "text_ar": "وأصحهما: يعتق ; لأنه كعضوها.",
      "text_en": "",
      "reference": "فصل"
    },
    {
      "id": 13007,
      "text_ar": "ولو قال:",
      "text_en": "",
      "reference": "فصل"
    },
    {
      "id": 13008,
      "text_ar": "هي حرة بعد موتي إلا جنينها، أو دون جنينها، لم يصح الاستثناء على الأصح.",
      "text_en": "",
      "reference": "فصل"
    },
    {
      "id": 13009,
      "text_ar": "ولو نجز عتقها في الحياة، عتق الحمل، ولم يصح استثناؤه بلا خلاف.",
      "text_en": "",
      "reference": "فصل"
    },
    {
      "id": 13010,
      "text_ar": "ولو كانت لشخص، وحملها لآخر، فأعتقها مالكها، لم يعتق الحمل قطعا ; لأن اختلاف الملك يمنع الاستتباع.",
      "text_en": "",
      "reference": "فصل"
    }
  ]
}